ctk_toggle/__init__.py
ctk_toggle/ctk_toggle_button.py
ctk_toggle/ctk_toggle_group.py
ctk_toggle-1.0.1.dist-info/LICENSE
ctk_toggle-1.0.1.dist-info/METADATA
ctk_toggle-1.0.1.dist-info/WHEEL
ctk_toggle-1.0.1.dist-info/top_level.txt
ctk_toggle-1.0.1.dist-info/RECORD
