Metadata-Version: 2.2
Name: ctk_toggle
Version: 1.0.1
Summary: A lightweight Python package for creating toggle buttons and groups using CustomTkinter.
Home-page: https://github.com/DeltaGa/ctk_toggle
Author: Tchicdje Kouojip Joram Smith (DeltaGa)
Author-email: dev.github.tkjoramsmith@outlook.com
License: MIT
Keywords: customtkinter tkinter toggle button UI
Classifier: Programming Language :: Python :: 3
Classifier: License :: OSI Approved :: MIT License
Classifier: Operating System :: OS Independent
Requires-Python: >=3.7
License-File: LICENSE
Requires-Dist: customtkinter>=5.1.0
Dynamic: author
Dynamic: author-email
Dynamic: classifier
Dynamic: description
Dynamic: description-content-type
Dynamic: home-page
Dynamic: keywords
Dynamic: license
Dynamic: requires-dist
Dynamic: requires-python
Dynamic: summary
